topsis/__init__.py
topsis/topsis.py
Topsis_Onkarjot_101903564-0.3.dist-info/LICENSE
Topsis_Onkarjot_101903564-0.3.dist-info/METADATA
Topsis_Onkarjot_101903564-0.3.dist-info/WHEEL
Topsis_Onkarjot_101903564-0.3.dist-info/entry_points.txt
Topsis_Onkarjot_101903564-0.3.dist-info/top_level.txt
Topsis_Onkarjot_101903564-0.3.dist-info/RECORD
